LICENSE
MANIFEST.in
README.rst
pyproject.toml
setup.py
pmesh/__init__.py
pmesh/_cic.py
pmesh/_domain.c
pmesh/_domain.pyx
pmesh/_invariant.c
pmesh/_invariant.pyx
pmesh/_invariant_imp.c
pmesh/_whitenoise.c
pmesh/_whitenoise.pyx
pmesh/_whitenoise_generics.h
pmesh/_whitenoise_imp.c
pmesh/_whitenoise_imp.h
pmesh/_window.c
pmesh/_window.pyx
pmesh/_window_acg.h
pmesh/_window_generics.h
pmesh/_window_imp.c
pmesh/_window_imp.h
pmesh/_window_lanczos.h
pmesh/_window_tuned_cic.h
pmesh/_window_tuned_nnb.h
pmesh/_window_tuned_pcs.h
pmesh/_window_tuned_tsc.h
pmesh/_window_wavelets.h
pmesh/abopt.py
pmesh/cic.py
pmesh/coarray.py
pmesh/domain.py
pmesh/invariant.py
pmesh/lanczos.py
pmesh/lic.py
pmesh/particlemesh.py
pmesh/pm.py
pmesh/tools.py
pmesh/transfer.py
pmesh/tsc.py
pmesh/version.py
pmesh/whitenoise.py
pmesh/window.py
pmesh.egg-info/PKG-INFO
pmesh.egg-info/SOURCES.txt
pmesh.egg-info/dependency_links.txt
pmesh.egg-info/requires.txt
pmesh.egg-info/top_level.txt
pmesh/gsl/config.h
pmesh/gsl/gsl_errno.h
pmesh/gsl/gsl_inline.h
pmesh/gsl/gsl_rng.h
pmesh/gsl/gsl_types.h
pmesh/gsl/missing.c
pmesh/gsl/ranlxd.c
pmesh/gsl/rng.c
pmesh/tests/__init__.py
pmesh/tests/test-particlemesh.py
pmesh/tests/test_abopt.py
pmesh/tests/test_domain.py
pmesh/tests/test_gradient.py
pmesh/tests/test_invariant.py
pmesh/tests/test_lic.py
pmesh/tests/test_pm.py
pmesh/tests/test_whitenoise.py
pmesh/tests/test_window.py