Metadata-Version: 2.4
Name: pmesh
Version: 0.1.58
Summary: Particle Mesh in Python
Author: Yu Feng
License: GPL3
License-File: LICENSE
Requires-Dist: cython
Requires-Dist: numpy
Requires-Dist: mpi4py
Requires-Dist: mpsort
Requires-Dist: pfft-python
Provides-Extra: full
Requires-Dist: abopt; extra == "full"
Provides-Extra: abopt
Requires-Dist: abopt; extra == "abopt"
Dynamic: author
Dynamic: license
Dynamic: license-file
Dynamic: provides-extra
Dynamic: requires-dist
Dynamic: summary
